coparser/__init__.py
coparser/amazon_com.py
coparser/main.py
coparser-0.0.4.dist-info/METADATA
coparser-0.0.4.dist-info/WHEEL
coparser-0.0.4.dist-info/licenses/LICENSE
coparser-0.0.4.dist-info/RECORD
