Metadata-Version: 2.4
Name: coparser
Version: 0.0.4
Summary: A small example package
Project-URL: Homepage, https://github.com/Coparser/Coparser
Project-URL: Issues, https://github.com/pypa/sampleproject/issues
Author-email: Example Author <author@example.com>
License-Expression: MIT
License-File: LICENSE
Classifier: Operating System :: OS Independent
Classifier: Programming Language :: Python :: 3
Requires-Python: >=3.8
